{
  "scoreCard": [
    {
      "matchId": 66484,
      "inningsId": 1,
      "timeScore": 1682523759000,
      "batTeamDetails": {
        "batTeamId": 63,
        "batTeamName": "Kolkata Knight Riders",
        "batTeamShortName": "KKR",
        "batsmenData": {
          "bat_1": {
            "batId": 6534,
            "batName": "Jason Roy",
            "batShortName": "",
            "isCaptain": false,
            "isKeeper": false,
            "runs": 56,
            "balls": 29,
            "dots": 0,
            "fours": 4,
            "sixes": 5,
            "mins": 0,
            "strikeRate": 193.1,
            "outDesc": "b Vijaykumar Vyshak",
            "bowlerId": 10486,
            "fielderId1": 0,
            "fielderId2": 0,
            "fielderId3": 0,
            "ones": 0,
            "twos": 0,
            "threes": 0,
            "fives": 0,
            "boundaries": 4,
            "sixers": 5,
            "wicketCode": "BOWLED",
            "isOverseas": true,
            "inMatchChange": "MOUT",
            "playingXIChange": ""
          },
          "bat_2": {
            "batId": 11675,
            "batName": "N Jagadeesan",
            "batShortName": "",
            "isCaptain": false,
            "isKeeper": true,
            "runs": 27,
            "balls": 29,
            "dots": 0,
            "fours": 4,
            "sixes": 0,
            "mins": 0,
            "strikeRate": 93.1,
            "outDesc": "c Willey b Vijaykumar Vyshak",
            "bowlerId": 10486,
            "fielderId1": 6592,
            "fielderId2": 0,
            "fielderId3": 0,
            "ones": 0,
            "twos": 0,
            "threes": 0,
            "fives": 0,
            "boundaries": 4,
            "sixers": 0,
            "wicketCode": "CAUGHT",
            "isOverseas": false,
            "inMatchChange": "",
            "playingXIChange": ""
          },
          "bat_3": {
            "batId": 10917,
            "batName": "Venkatesh Iyer",
            "batShortName": "",
            "isCaptain": false,
            "isKeeper": false,
            "runs": 31,
            "balls": 26,
            "dots": 0,
            "fours": 3,
            "sixes": 0,
            "mins": 0,
            "strikeRate": 119.23,
            "outDesc": "c Maxwell b W Hasaranga",
            "bowlerId": 10926,
            "fielderId1": 7662,
            "fielderId2": 0,
            "fielderId3": 0,
            "ones": 0,
            "twos": 0,
            "threes": 0,
            "fives": 0,
            "boundaries": 3,
            "sixers": 0,
            "wicketCode": "CAUGHT",
            "isOverseas": false,
            "inMatchChange": "",
            "playingXIChange": "IN"
          },
          "bat_4": {
            "batId": 9204,
            "batName": "Nitish Rana",
            "batShortName": "",
            "isCaptain": true,
            "isKeeper": false,
            "runs": 48,
            "balls": 21,
            "dots": 0,
            "fours": 3,
            "sixes": 4,
            "mins": 0,
            "strikeRate": 228.57,
            "outDesc": "c Vijaykumar Vyshak b W Hasaranga",
            "bowlerId": 10926,
            "fielderId1": 10486,
            "fielderId2": 0,
            "fielderId3": 0,
            "ones": 0,
            "twos": 0,
            "threes": 0,
            "fives": 0,
            "boundaries": 3,
            "sixers": 4,
            "wicketCode": "CAUGHT",
            "isOverseas": false,
            "inMatchChange": "",
            "playingXIChange": ""
          },
          "bat_5": {
            "batId": 7736,
            "batName": "Russell",
            "batShortName": "",
            "isCaptain": false,
            "isKeeper": false,
            "runs": 1,
            "balls": 2,
            "dots": 0,
            "fours": 0,
            "sixes": 0,
            "mins": 0,
            "strikeRate": 50.0,
            "outDesc": "b Siraj",
            "bowlerId": 10808,
            "fielderId1": 0,
            "fielderId2": 0,
            "fielderId3": 0,
            "ones": 0,
            "twos": 0,
            "threes": 0,
            "fives": 0,
            "boundaries": 0,
            "sixers": 0,
            "wicketCode": "BOWLED",
            "isOverseas": true,
            "inMatchChange": "",
            "playingXIChange": ""
          },
          "bat_6": {
            "batId": 10896,
            "batName": "Rinku Singh",
            "batShortName": "",
            "isCaptain": false,
            "isKeeper": false,
            "runs": 18,
            "balls": 10,
            "dots": 0,
            "fours": 2,
            "sixes": 1,
            "mins": 0,
            "strikeRate": 180.0,
            "outDesc": "not out",
            "bowlerId": 0,
            "fielderId1": 0,
            "fielderId2": 0,
            "fielderId3": 0,
            "ones": 0,
            "twos": 0,
            "threes": 0,
            "fives": 0,
            "boundaries": 2,
            "sixers": 1,
            "wicketCode": "",
            "isOverseas": false,
            "inMatchChange": "",
            "playingXIChange": ""
          },
          "bat_7": {
            "batId": 8589,
            "batName": "Wiese",
            "batShortName": "",
            "isCaptain": false,
            "isKeeper": false,
            "runs": 12,
            "balls": 3,
            "dots": 0,
            "fours": 0,
            "sixes": 2,
            "mins": 0,
            "strikeRate": 400.0,
            "outDesc": "not out",
            "bowlerId": 0,
            "fielderId1": 0,
            "fielderId2": 0,
            "fielderId3": 0,
            "ones": 0,
            "twos": 0,
            "threes": 0,
            "fives": 0,
            "boundaries": 0,
            "sixers": 2,
            "wicketCode": "",
            "isOverseas": true,
            "inMatchChange": "",
            "playingXIChange": ""
          },
          "bat_8": {
            "batId": 2276,
            "batName": "Narine",
            "batShortName": "",
            "isCaptain": false,
            "isKeeper": false,
            "runs": 0,
            "balls": 0,
            "dots": 0,
            "fours": 0,
            "sixes": 0,
            "mins": 0,
            "strikeRate": 0.0,
            "outDesc": "",
            "bowlerId": 0,
            "fielderId1": 0,
            "fielderId2": 0,
            "fielderId3": 0,
            "ones": 0,
            "twos": 0,
            "threes": 0,
            "fives": 0,
            "boundaries": 0,
            "sixers": 0,
            "wicketCode": "",
            "isOverseas": true,
            "inMatchChange": "",
            "playingXIChange": ""
          },
          "bat_9": {
            "batId": 15861,
            "batName": "Vaibhav Arora",
            "batShortName": "",
            "isCaptain": false,
            "isKeeper": false,
            "runs": 0,
            "balls": 0,
            "dots": 0,
            "fours": 0,
            "sixes": 0,
            "mins": 0,
            "strikeRate": 0.0,
            "outDesc": "",
            "bowlerId": 0,
            "fielderId1": 0,
            "fielderId2": 0,
            "fielderId3": 0,
            "ones": 0,
            "twos": 0,
            "threes": 0,
            "fives": 0,
            "boundaries": 0,
            "sixers": 0,
            "wicketCode": "",
            "isOverseas": false,
            "inMatchChange": "",
            "playingXIChange": "IN"
          },
          "bat_10": {
            "batId": 1858,
            "batName": "Umesh",
            "batShortName": "",
            "isCaptain": false,
            "isKeeper": false,
            "runs": 0,
            "balls": 0,
            "dots": 0,
            "fours": 0,
            "sixes": 0,
            "mins": 0,
            "strikeRate": 0.0,
            "outDesc": "",
            "bowlerId": 0,
            "fielderId1": 0,
            "fielderId2": 0,
            "fielderId3": 0,
            "ones": 0,
            "twos": 0,
            "threes": 0,
            "fives": 0,
            "boundaries": 0,
            "sixers": 0,
            "wicketCode": "",
            "isOverseas": false,
            "inMatchChange": "",
            "playingXIChange": ""
          },
          "bat_11": {
            "batId": 12926,
            "batName": "Chakaravarthy",
            "batShortName": "",
            "isCaptain": false,
            "isKeeper": false,
            "runs": 0,
            "balls": 0,
            "dots": 0,
            "fours": 0,
            "sixes": 0,
            "mins": 0,
            "strikeRate": 0.0,
            "outDesc": "",
            "bowlerId": 0,
            "fielderId1": 0,
            "fielderId2": 0,
            "fielderId3": 0,
            "ones": 0,
            "twos": 0,
            "threes": 0,
            "fives": 0,
            "boundaries": 0,
            "sixers": 0,
            "wicketCode": "",
            "isOverseas": false,
            "inMatchChange": "",
            "playingXIChange": ""
          },
          "bat_12": {
            "batId": 36487,
            "batName": "Suyash Sharma",
            "batShortName": "",
            "isCaptain": false,
            "isKeeper": false,
            "runs": 0,
            "balls": 0,
            "dots": 0,
            "fours": 0,
            "sixes": 0,
            "mins": 0,
            "strikeRate": 0.0,
            "outDesc": "",
            "bowlerId": 0,
            "fielderId1": 0,
            "fielderId2": 0,
            "fielderId3": 0,
            "ones": 0,
            "twos": 0,
            "threes": 0,
            "fives": 0,
            "boundaries": 0,
            "sixers": 0,
            "wicketCode": "",
            "isOverseas": false,
            "inMatchChange": "MIN",
            "playingXIChange": "OUT"
          }
        }
      },
      "bowlTeamDetails": {
        "bowlTeamId": 59,
        "bowlTeamName": "Royal Challengers Bangalore",
        "bowlTeamShortName": "RCB",
        "bowlersData": {
          "bowl_1": {
            "bowlerId": 10808,
            "bowlName": "Siraj",
            "bowlShortName": "",
            "isCaptain": false,
            "isKeeper": false,
            "overs": 4.0,
            "maidens": 0,
            "runs": 33,
            "wickets": 1,
            "economy": 8.2,
            "no_balls": 0,
            "wides": 0,
            "dots": 0,
            "balls": 0,
            "runsPerBall": 0.0,
            "isOverseas": false,
            "inMatchChange": "",
            "playingXIChange": ""
          },
          "bowl_2": {
            "bowlerId": 6592,
            "bowlName": "Willey",
            "bowlShortName": "",
            "isCaptain": false,
            "isKeeper": false,
            "overs": 3.0,
            "maidens": 0,
            "runs": 31,
            "wickets": 0,
            "economy": 10.3,
            "no_balls": 0,
            "wides": 1,
            "dots": 0,
            "balls": 0,
            "runsPerBall": 0.0,
            "isOverseas": true,
            "inMatchChange": "",
            "playingXIChange": ""
          },
          "bowl_3": {
            "bowlerId": 10926,
            "bowlName": "W Hasaranga",
            "bowlShortName": "",
            "isCaptain": false,
            "isKeeper": false,
            "overs": 4.0,
            "maidens": 0,
            "runs": 24,
            "wickets": 2,
            "economy": 6.0,
            "no_balls": 0,
            "wides": 0,
            "dots": 0,
            "balls": 0,
            "runsPerBall": 0.0,
            "isOverseas": true,
            "inMatchChange": "",
            "playingXIChange": ""
          },
          "bowl_4": {
            "bowlerId": 14606,
            "bowlName": "Shahbaz Ahmed",
            "bowlShortName": "",
            "isCaptain": false,
            "isKeeper": false,
            "overs": 1.0,
            "maidens": 0,
            "runs": 25,
            "wickets": 0,
            "economy": 25.0,
            "no_balls": 0,
            "wides": 0,
            "dots": 0,
            "balls": 0,
            "runsPerBall": 0.0,
            "isOverseas": false,
            "inMatchChange": "",
            "playingXIChange": ""
          },
          "bowl_5": {
            "bowlerId": 10486,
            "bowlName": "Vijaykumar Vyshak",
            "bowlShortName": "",
            "isCaptain": false,
            "isKeeper": false,
            "overs": 4.0,
            "maidens": 0,
            "runs": 41,
            "wickets": 2,
            "economy": 10.2,
            "no_balls": 0,
            "wides": 3,
            "dots": 0,
            "balls": 0,
            "runsPerBall": 0.0,
            "isOverseas": false,
            "inMatchChange": "",
            "playingXIChange": ""
          },
          "bowl_6": {
            "bowlerId": 8175,
            "bowlName": "Harshal Patel",
            "bowlShortName": "",
            "isCaptain": false,
            "isKeeper": false,
            "overs": 4.0,
            "maidens": 0,
            "runs": 44,
            "wickets": 0,
            "economy": 11.0,
            "no_balls": 0,
            "wides": 1,
            "dots": 0,
            "balls": 0,
            "runsPerBall": 0.0,
            "isOverseas": false,
            "inMatchChange": "MOUT",
            "playingXIChange": "IN"
          }
        }
      },
      "scoreDetails": {
        "ballNbr": 120,
        "isDeclared": false,
        "isFollowOn": false,
        "overs": 20.0,
        "revisedOvers": 0.0,
        "runRate": 10.0,
        "runs": 200,
        "wickets": 5,
        "runsPerBall": 1.0
      },
      "extrasData": {
        "noBalls": 0,
        "total": 7,
        "byes": 0,
        "penalty": 0,
        "wides": 5,
        "legByes": 2
      },
      "ppData": {
        "pp_1": {
          "ppId": 5,
          "ppOversFrom": 0.1,
          "ppOversTo": 6.0,
          "ppType": "mandatory",
          "runsScored": 66
        }
      },
      "wicketsData": {
        "wkt_1": {
          "batId": 11675,
          "batName": "N Jagadeesan",
          "wktNbr": 1,
          "wktOver": 9.2,
          "wktRuns": 83,
          "ballNbr": 92
        },
        "wkt_2": {
          "batId": 6534,
          "batName": "Jason Roy",
          "wktNbr": 2,
          "wktOver": 9.6,
          "wktRuns": 88,
          "ballNbr": 96
        },
        "wkt_3": {
          "batId": 9204,
          "batName": "Nitish Rana",
          "wktNbr": 3,
          "wktOver": 17.2,
          "wktRuns": 168,
          "ballNbr": 172
        },
        "wkt_4": {
          "batId": 10917,
          "batName": "Venkatesh Iyer",
          "wktNbr": 4,
          "wktOver": 17.4,
          "wktRuns": 169,
          "ballNbr": 174
        },
        "wkt_5": {
          "batId": 7736,
          "batName": "Russell",
          "wktNbr": 5,
          "wktOver": 18.6,
          "wktRuns": 185,
          "ballNbr": 186
        }
      },
      "partnershipsData": {
        "pat_1": {
          "bat1Id": 6534,
          "bat1Name": "Roy",
          "bat1Runs": 55,
          "bat1fours": 4,
          "bat1sixes": 5,
          "bat2Id": 11675,
          "bat2Name": "N Jagadeesan",
          "bat2Runs": 27,
          "bat2fours": 4,
          "bat2sixes": 0,
          "totalRuns": 83,
          "totalBalls": 56,
          "bat1balls": 0,
          "bat2balls": 0,
          "bat1Ones": 0,
          "bat1Twos": 0,
          "bat1Threes": 0,
          "bat1Fives": 0,
          "bat1Boundaries": 0,
          "bat1Sixers": 0,
          "bat2Ones": 0,
          "bat2Twos": 0,
          "bat2Threes": 0,
          "bat2Fives": 0,
          "bat2Boundaries": 0,
          "bat2Sixers": 0
        },
        "pat_2": {
          "bat1Id": 6534,
          "bat1Name": "Roy",
          "bat1Runs": 1,
          "bat1fours": 0,
          "bat1sixes": 0,
          "bat2Id": 10917,
          "bat2Name": "Venkatesh Iyer",
          "bat2Runs": 2,
          "bat2fours": 0,
          "bat2sixes": 0,
          "totalRuns": 5,
          "totalBalls": 4,
          "bat1balls": 0,
          "bat2balls": 0,
          "bat1Ones": 0,
          "bat1Twos": 0,
          "bat1Threes": 0,
          "bat1Fives": 0,
          "bat1Boundaries": 0,
          "bat1Sixers": 0,
          "bat2Ones": 0,
          "bat2Twos": 0,
          "bat2Threes": 0,
          "bat2Fives": 0,
          "bat2Boundaries": 0,
          "bat2Sixers": 0
        },
        "pat_3": {
          "bat1Id": 9204,
          "bat1Name": "Nitish Rana",
          "bat1Runs": 48,
          "bat1fours": 3,
          "bat1sixes": 4,
          "bat2Id": 10917,
          "bat2Name": "Venkatesh Iyer",
          "bat2Runs": 29,
          "bat2fours": 3,
          "bat2sixes": 0,
          "totalRuns": 80,
          "totalBalls": 44,
          "bat1balls": 0,
          "bat2balls": 0,
          "bat1Ones": 0,
          "bat1Twos": 0,
          "bat1Threes": 0,
          "bat1Fives": 0,
          "bat1Boundaries": 0,
          "bat1Sixers": 0,
          "bat2Ones": 0,
          "bat2Twos": 0,
          "bat2Threes": 0,
          "bat2Fives": 0,
          "bat2Boundaries": 0,
          "bat2Sixers": 0
        },
        "pat_4": {
          "bat1Id": 7736,
          "bat1Name": "Russell",
          "bat1Runs": 1,
          "bat1fours": 0,
          "bat1sixes": 0,
          "bat2Id": 10917,
          "bat2Name": "Venkatesh Iyer",
          "bat2Runs": 0,
          "bat2fours": 0,
          "bat2sixes": 0,
          "totalRuns": 1,
          "totalBalls": 2,
          "bat1balls": 0,
          "bat2balls": 0,
          "bat1Ones": 0,
          "bat1Twos": 0,
          "bat1Threes": 0,
          "bat1Fives": 0,
          "bat1Boundaries": 0,
          "bat1Sixers": 0,
          "bat2Ones": 0,
          "bat2Twos": 0,
          "bat2Threes": 0,
          "bat2Fives": 0,
          "bat2Boundaries": 0,
          "bat2Sixers": 0
        },
        "pat_5": {
          "bat1Id": 7736,
          "bat1Name": "Russell",
          "bat1Runs": 0,
          "bat1fours": 0,
          "bat1sixes": 0,
          "bat2Id": 10896,
          "bat2Name": "Rinku Singh",
          "bat2Runs": 16,
          "bat2fours": 2,
          "bat2sixes": 1,
          "totalRuns": 16,
          "totalBalls": 8,
          "bat1balls": 0,
          "bat2balls": 0,
          "bat1Ones": 0,
          "bat1Twos": 0,
          "bat1Threes": 0,
          "bat1Fives": 0,
          "bat1Boundaries": 0,
          "bat1Sixers": 0,
          "bat2Ones": 0,
          "bat2Twos": 0,
          "bat2Threes": 0,
          "bat2Fives": 0,
          "bat2Boundaries": 0,
          "bat2Sixers": 0
        },
        "pat_6": {
          "bat1Id": 8589,
          "bat1Name": "Wiese",
          "bat1Runs": 12,
          "bat1fours": 0,
          "bat1sixes": 2,
          "bat2Id": 10896,
          "bat2Name": "Rinku Singh",
          "bat2Runs": 2,
          "bat2fours": 0,
          "bat2sixes": 0,
          "totalRuns": 15,
          "totalBalls": 6,
          "bat1balls": 0,
          "bat2balls": 0,
          "bat1Ones": 0,
          "bat1Twos": 0,
          "bat1Threes": 0,
          "bat1Fives": 0,
          "bat1Boundaries": 0,
          "bat1Sixers": 0,
          "bat2Ones": 0,
          "bat2Twos": 0,
          "bat2Threes": 0,
          "bat2Fives": 0,
          "bat2Boundaries": 0,
          "bat2Sixers": 0
        }
      }
    },
    {
      "matchId": 66484,
      "inningsId": 2,
      "timeScore": 1682530854000,
      "batTeamDetails": {
        "batTeamId": 59,
        "batTeamName": "Royal Challengers Bangalore",
        "batTeamShortName": "RCB",
        "batsmenData": {
          "bat_1": {
            "batId": 1413,
            "batName": "Virat Kohli",
            "batShortName": "Kohli",
            "isCaptain": true,
            "isKeeper": false,
            "runs": 54,
            "balls": 37,
            "dots": 5,
            "fours": 6,
            "sixes": 0,
            "mins": 59,
            "strikeRate": 145.95,
            "outDesc": "c Venkatesh Iyer b Russell",
            "bowlerId": 7736,
            "fielderId1": 10917,
            "fielderId2": 0,
            "fielderId3": 0,
            "ones": 22,
            "twos": 4,
            "threes": 0,
            "fives": 0,
            "boundaries": 6,
            "sixers": 0,
            "wicketCode": "CAUGHT",
            "isOverseas": false,
            "inMatchChange": "",
            "playingXIChange": ""
          },
          "bat_2": {
            "batId": 7825,
            "batName": "Faf du Plessis",
            "batShortName": "du Plessis",
            "isCaptain": false,
            "isKeeper": false,
            "runs": 17,
            "balls": 7,
            "dots": 3,
            "fours": 1,
            "sixes": 2,
            "mins": 10,
            "strikeRate": 242.86,
            "outDesc": "c Rinku Singh b Suyash Sharma",
            "bowlerId": 36487,
            "fielderId1": 10896,
            "fielderId2": 0,
            "fielderId3": 0,
            "ones": 1,
            "twos": 0,
            "threes": 0,
            "fives": 0,
            "boundaries": 1,
            "sixers": 2,
            "wicketCode": "CAUGHT",
            "isOverseas": true,
            "inMatchChange": "MIN",
            "playingXIChange": "OUT"
          },
          "bat_3": {
            "batId": 14606,
            "batName": "Shahbaz Ahmed",
            "batShortName": "Shahbaz Ahmed",
            "isCaptain": false,
            "isKeeper": false,
            "runs": 2,
            "balls": 5,
            "dots": 3,
            "fours": 0,
            "sixes": 0,
            "mins": 9,
            "strikeRate": 40.0,
            "outDesc": "lbw b Suyash Sharma",
            "bowlerId": 36487,
            "fielderId1": 0,
            "fielderId2": 0,
            "fielderId3": 0,
            "ones": 2,
            "twos": 0,
            "threes": 0,
            "fives": 0,
            "boundaries": 0,
            "sixers": 0,
            "wicketCode": "LBW",
            "isOverseas": false,
            "inMatchChange": "",
            "playingXIChange": ""
          },
          "bat_4": {
            "batId": 7662,
            "batName": "Glenn Maxwell",
            "batShortName": "Maxwell",
            "isCaptain": false,
            "isKeeper": false,
            "runs": 5,
            "balls": 4,
            "dots": 2,
            "fours": 1,
            "sixes": 0,
            "mins": 4,
            "strikeRate": 125.0,
            "outDesc": "c Wiese b Chakaravarthy",
            "bowlerId": 12926,
            "fielderId1": 8589,
            "fielderId2": 0,
            "fielderId3": 0,
            "ones": 1,
            "twos": 0,
            "threes": 0,
            "fives": 0,
            "boundaries": 1,
            "sixers": 0,
            "wicketCode": "CAUGHT",
            "isOverseas": true,
            "inMatchChange": "",
            "playingXIChange": ""
          },
          "bat_5": {
            "batId": 10954,
            "batName": "Mahipal Lomror",
            "batShortName": "Lomror",
            "isCaptain": false,
            "isKeeper": false,
            "runs": 34,
            "balls": 18,
            "dots": 4,
            "fours": 1,
            "sixes": 3,
            "mins": 27,
            "strikeRate": 188.89,
            "outDesc": "c Russell b Chakaravarthy",
            "bowlerId": 12926,
            "fielderId1": 7736,
            "fielderId2": 0,
            "fielderId3": 0,
            "ones": 8,
            "twos": 2,
            "threes": 0,
            "fives": 0,
            "boundaries": 1,
            "sixers": 3,
            "wicketCode": "CAUGHT",
            "isOverseas": false,
            "inMatchChange": "",
            "playingXIChange": ""
          },
          "bat_6": {
            "batId": 145,
            "batName": "Dinesh Karthik",
            "batShortName": "Karthik",
            "isCaptain": false,
            "isKeeper": true,
            "runs": 22,
            "balls": 18,
            "dots": 5,
            "fours": 1,
            "sixes": 1,
            "mins": 34,
            "strikeRate": 122.22,
            "outDesc": "c Rinku Singh b Chakaravarthy",
            "bowlerId": 12926,
            "fielderId1": 10896,
            "fielderId2": 0,
            "fielderId3": 0,
            "ones": 10,
            "twos": 1,
            "threes": 0,
            "fives": 0,
            "boundaries": 1,
            "sixers": 1,
            "wicketCode": "CAUGHT",
            "isOverseas": false,
            "inMatchChange": "",
            "playingXIChange": ""
          },
          "bat_7": {
            "batId": 12669,
            "batName": "Suyash Prabhudessai",
            "batShortName": "Prabhudessai",
            "isCaptain": false,
            "isKeeper": false,
            "runs": 10,
            "balls": 9,
            "dots": 4,
            "fours": 1,
            "sixes": 0,
            "mins": 13,
            "strikeRate": 111.11,
            "outDesc": "run out ((sub)Anukul Roy/Suyash Sharma)",
            "bowlerId": 0,
            "fielderId1": 12344,
            "fielderId2": 36487,
            "fielderId3": 0,
            "ones": 2,
            "twos": 2,
            "threes": 0,
            "fives": 0,
            "boundaries": 1,
            "sixers": 0,
            "wicketCode": "RUNOUT",
            "isOverseas": false,
            "inMatchChange": "",
            "playingXIChange": ""
          },
          "bat_8": {
            "batId": 10926,
            "batName": "Wanindu Hasaranga",
            "batShortName": "W Hasaranga",
            "isCaptain": false,
            "isKeeper": false,
            "runs": 5,
            "balls": 4,
            "dots": 1,
            "fours": 0,
            "sixes": 0,
            "mins": 11,
            "strikeRate": 125.0,
            "outDesc": "c (sub)Anukul Roy b Russell",
            "bowlerId": 7736,
            "fielderId1": 12344,
            "fielderId2": 0,
            "fielderId3": 0,
            "ones": 1,
            "twos": 2,
            "threes": 0,
            "fives": 0,
            "boundaries": 0,
            "sixers": 0,
            "wicketCode": "CAUGHT",
            "isOverseas": true,
            "inMatchChange": "",
            "playingXIChange": ""
          },
          "bat_9": {
            "batId": 6592,
            "batName": "David Willey",
            "batShortName": "Willey",
            "isCaptain": false,
            "isKeeper": false,
            "runs": 11,
            "balls": 10,
            "dots": 3,
            "fours": 1,
            "sixes": 0,
            "mins": 15,
            "strikeRate": 110.0,
            "outDesc": "not out",
            "bowlerId": 0,
            "fielderId1": 0,
            "fielderId2": 0,
            "fielderId3": 0,
            "ones": 5,
            "twos": 1,
            "threes": 0,
            "fives": 0,
            "boundaries": 1,
            "sixers": 0,
            "wicketCode": "",
            "isOverseas": true,
            "inMatchChange": "",
            "playingXIChange": ""
          },
          "bat_10": {
            "batId": 10486,
            "batName": "Vijaykumar Vyshak",
            "batShortName": "Vijaykumar Vyshak",
            "isCaptain": false,
            "isKeeper": false,
            "runs": 13,
            "balls": 8,
            "dots": 1,
            "fours": 0,
            "sixes": 1,
            "mins": 11,
            "strikeRate": 162.5,
            "outDesc": "not out",
            "bowlerId": 0,
            "fielderId1": 0,
            "fielderId2": 0,
            "fielderId3": 0,
            "ones": 5,
            "twos": 1,
            "threes": 0,
            "fives": 0,
            "boundaries": 0,
            "sixers": 1,
            "wicketCode": "",
            "isOverseas": false,
            "inMatchChange": "",
            "playingXIChange": ""
          },
          "bat_11": {
            "batId": 8175,
            "batName": "Harshal Patel",
            "batShortName": "Harshal Patel",
            "isCaptain": false,
            "isKeeper": false,
            "runs": 0,
            "balls": 0,
            "dots": 0,
            "fours": 0,
            "sixes": 0,
            "mins": 0,
            "strikeRate": 0.0,
            "outDesc": "",
            "bowlerId": 0,
            "fielderId1": 0,
            "fielderId2": 0,
            "fielderId3": 0,
            "ones": 0,
            "twos": 0,
            "threes": 0,
            "fives": 0,
            "boundaries": 0,
            "sixers": 0,
            "wicketCode": "",
            "isOverseas": false,
            "inMatchChange": "MOUT",
            "playingXIChange": "IN"
          },
          "bat_12": {
            "batId": 10808,
            "batName": "Mohammed Siraj",
            "batShortName": "Siraj",
            "isCaptain": false,
            "isKeeper": false,
            "runs": 0,
            "balls": 0,
            "dots": 0,
            "fours": 0,
            "sixes": 0,
            "mins": 0,
            "strikeRate": 0.0,
            "outDesc": "",
            "bowlerId": 0,
            "fielderId1": 0,
            "fielderId2": 0,
            "fielderId3": 0,
            "ones": 0,
            "twos": 0,
            "threes": 0,
            "fives": 0,
            "boundaries": 0,
            "sixers": 0,
            "wicketCode": "",
            "isOverseas": false,
            "inMatchChange": "",
            "playingXIChange": ""
          }
        }
      },
      "bowlTeamDetails": {
        "bowlTeamId": 63,
        "bowlTeamName": "Kolkata Knight Riders",
        "bowlTeamShortName": "KKR",
        "bowlersData": {
          "bowl_1": {
            "bowlerId": 15861,
            "bowlName": "Vaibhav Arora",
            "bowlShortName": "Vaibhav Arora",
            "isCaptain": false,
            "isKeeper": false,
            "overs": 2.0,
            "maidens": 0,
            "runs": 22,
            "wickets": 0,
            "economy": 11.0,
            "no_balls": 0,
            "wides": 2,
            "dots": 0,
            "balls": 0,
            "runsPerBall": 0.0,
            "isOverseas": false,
            "inMatchChange": "",
            "playingXIChange": "IN"
          },
          "bowl_2": {
            "bowlerId": 1858,
            "bowlName": "Umesh Yadav",
            "bowlShortName": "Umesh",
            "isCaptain": false,
            "isKeeper": false,
            "overs": 1.0,
            "maidens": 0,
            "runs": 19,
            "wickets": 0,
            "economy": 19.0,
            "no_balls": 0,
            "wides": 0,
            "dots": 0,
            "balls": 0,
            "runsPerBall": 0.0,
            "isOverseas": false,
            "inMatchChange": "",
            "playingXIChange": ""
          },
          "bowl_3": {
            "bowlerId": 36487,
            "bowlName": "Suyash Sharma",
            "bowlShortName": "Suyash Sharma",
            "isCaptain": false,
            "isKeeper": false,
            "overs": 4.0,
            "maidens": 0,
            "runs": 30,
            "wickets": 2,
            "economy": 7.5,
            "no_balls": 0,
            "wides": 1,
            "dots": 0,
            "balls": 0,
            "runsPerBall": 0.0,
            "isOverseas": false,
            "inMatchChange": "MIN",
            "playingXIChange": "OUT"
          },
          "bowl_4": {
            "bowlerId": 12926,
            "bowlName": "Varun Chakaravarthy",
            "bowlShortName": "Chakaravarthy",
            "isCaptain": false,
            "isKeeper": false,
            "overs": 4.0,
            "maidens": 0,
            "runs": 27,
            "wickets": 3,
            "economy": 6.8,
            "no_balls": 0,
            "wides": 0,
            "dots": 0,
            "balls": 0,
            "runsPerBall": 0.0,
            "isOverseas": false,
            "inMatchChange": "",
            "playingXIChange": ""
          },
          "bowl_5": {
            "bowlerId": 7736,
            "bowlName": "Andre Russell",
            "bowlShortName": "Russell",
            "isCaptain": false,
            "isKeeper": false,
            "overs": 4.0,
            "maidens": 0,
            "runs": 29,
            "wickets": 2,
            "economy": 7.2,
            "no_balls": 0,
            "wides": 0,
            "dots": 0,
            "balls": 0,
            "runsPerBall": 0.0,
            "isOverseas": true,
            "inMatchChange": "",
            "playingXIChange": ""
          },
          "bowl_6": {
            "bowlerId": 2276,
            "bowlName": "Sunil Narine",
            "bowlShortName": "Narine",
            "isCaptain": false,
            "isKeeper": false,
            "overs": 4.0,
            "maidens": 0,
            "runs": 41,
            "wickets": 0,
            "economy": 10.2,
            "no_balls": 0,
            "wides": 0,
            "dots": 0,
            "balls": 0,
            "runsPerBall": 0.0,
            "isOverseas": true,
            "inMatchChange": "",
            "playingXIChange": ""
          },
          "bowl_7": {
            "bowlerId": 9204,
            "bowlName": "Nitish Rana",
            "bowlShortName": "Nitish Rana",
            "isCaptain": true,
            "isKeeper": false,
            "overs": 1.0,
            "maidens": 0,
            "runs": 8,
            "wickets": 0,
            "economy": 8.0,
            "no_balls": 0,
            "wides": 0,
            "dots": 0,
            "balls": 0,
            "runsPerBall": 0.0,
            "isOverseas": false,
            "inMatchChange": "",
            "playingXIChange": ""
          }
        }
      },
      "scoreDetails": {
        "ballNbr": 120,
        "isDeclared": false,
        "isFollowOn": false,
        "overs": 20.0,
        "revisedOvers": 0.0,
        "runRate": 8.95,
        "runs": 179,
        "wickets": 8,
        "runsPerBall": 0.9
      },
      "extrasData": {
        "noBalls": 0,
        "total": 6,
        "byes": 0,
        "penalty": 0,
        "wides": 3,
        "legByes": 3
      },
      "ppData": {
        "pp_1": {
          "ppId": 6,
          "ppOversFrom": 0.1,
          "ppOversTo": 6.0,
          "ppType": "mandatory",
          "runsScored": 58
        }
      },
      "wicketsData": {
        "wkt_1": {
          "batId": 7825,
          "batName": "Faf du Plessis",
          "wktNbr": 1,
          "wktOver": 2.2,
          "wktRuns": 31,
          "ballNbr": 22
        },
        "wkt_2": {
          "batId": 14606,
          "batName": "Shahbaz Ahmed",
          "wktNbr": 2,
          "wktOver": 4.4,
          "wktRuns": 51,
          "ballNbr": 44
        },
        "wkt_3": {
          "batId": 7662,
          "batName": "Glenn Maxwell",
          "wktNbr": 3,
          "wktOver": 5.5,
          "wktRuns": 58,
          "ballNbr": 55
        },
        "wkt_4": {
          "batId": 10954,
          "batName": "Mahipal Lomror",
          "wktNbr": 4,
          "wktOver": 11.3,
          "wktRuns": 113,
          "ballNbr": 113
        },
        "wkt_5": {
          "batId": 1413,
          "batName": "Virat Kohli",
          "wktNbr": 5,
          "wktOver": 12.1,
          "wktRuns": 115,
          "ballNbr": 121
        },
        "wkt_6": {
          "batId": 12669,
          "batName": "Suyash Prabhudessai",
          "wktNbr": 6,
          "wktOver": 14.5,
          "wktRuns": 137,
          "ballNbr": 145
        },
        "wkt_7": {
          "batId": 10926,
          "batName": "Wanindu Hasaranga",
          "wktNbr": 7,
          "wktOver": 16.5,
          "wktRuns": 152,
          "ballNbr": 165
        },
        "wkt_8": {
          "batId": 145,
          "batName": "Dinesh Karthik",
          "wktNbr": 8,
          "wktOver": 17.3,
          "wktRuns": 154,
          "ballNbr": 173
        }
      },
      "partnershipsData": {
        "pat_1": {
          "bat1Id": 1413,
          "bat1Name": "Kohli",
          "bat1Runs": 13,
          "bat1fours": 2,
          "bat1sixes": 0,
          "bat2Id": 7825,
          "bat2Name": "du Plessis",
          "bat2Runs": 17,
          "bat2fours": 1,
          "bat2sixes": 2,
          "totalRuns": 31,
          "totalBalls": 14,
          "bat1balls": 7,
          "bat2balls": 7,
          "bat1Ones": 5,
          "bat1Twos": 0,
          "bat1Threes": 0,
          "bat1Fives": 0,
          "bat1Boundaries": 2,
          "bat1Sixers": 0,
          "bat2Ones": 1,
          "bat2Twos": 0,
          "bat2Threes": 0,
          "bat2Fives": 0,
          "bat2Boundaries": 1,
          "bat2Sixers": 2
        },
        "pat_2": {
          "bat1Id": 1413,
          "bat1Name": "Kohli",
          "bat1Runs": 18,
          "bat1fours": 3,
          "bat1sixes": 0,
          "bat2Id": 14606,
          "bat2Name": "Shahbaz Ahmed",
          "bat2Runs": 2,
          "bat2fours": 0,
          "bat2sixes": 0,
          "totalRuns": 20,
          "totalBalls": 14,
          "bat1balls": 9,
          "bat2balls": 5,
          "bat1Ones": 4,
          "bat1Twos": 1,
          "bat1Threes": 0,
          "bat1Fives": 0,
          "bat1Boundaries": 3,
          "bat1Sixers": 0,
          "bat2Ones": 2,
          "bat2Twos": 0,
          "bat2Threes": 0,
          "bat2Fives": 0,
          "bat2Boundaries": 0,
          "bat2Sixers": 0
        },
        "pat_3": {
          "bat1Id": 1413,
          "bat1Name": "Kohli",
          "bat1Runs": 2,
          "bat1fours": 0,
          "bat1sixes": 0,
          "bat2Id": 7662,
          "bat2Name": "Maxwell",
          "bat2Runs": 5,
          "bat2fours": 1,
          "bat2sixes": 0,
          "totalRuns": 7,
          "totalBalls": 7,
          "bat1balls": 3,
          "bat2balls": 4,
          "bat1Ones": 2,
          "bat1Twos": 0,
          "bat1Threes": 0,
          "bat1Fives": 0,
          "bat1Boundaries": 0,
          "bat1Sixers": 0,
          "bat2Ones": 1,
          "bat2Twos": 0,
          "bat2Threes": 0,
          "bat2Fives": 0,
          "bat2Boundaries": 1,
          "bat2Sixers": 0
        },
        "pat_4": {
          "bat1Id": 1413,
          "bat1Name": "Kohli",
          "bat1Runs": 20,
          "bat1fours": 1,
          "bat1sixes": 0,
          "bat2Id": 10954,
          "bat2Name": "Lomror",
          "bat2Runs": 34,
          "bat2fours": 1,
          "bat2sixes": 3,
          "totalRuns": 55,
          "totalBalls": 34,
          "bat1balls": 16,
          "bat2balls": 18,
          "bat1Ones": 10,
          "bat1Twos": 3,
          "bat1Threes": 0,
          "bat1Fives": 0,
          "bat1Boundaries": 1,
          "bat1Sixers": 0,
          "bat2Ones": 8,
          "bat2Twos": 2,
          "bat2Threes": 0,
          "bat2Fives": 0,
          "bat2Boundaries": 1,
          "bat2Sixers": 3
        },
        "pat_5": {
          "bat1Id": 1413,
          "bat1Name": "Kohli",
          "bat1Runs": 1,
          "bat1fours": 0,
          "bat1sixes": 0,
          "bat2Id": 145,
          "bat2Name": "Karthik",
          "bat2Runs": 1,
          "bat2fours": 0,
          "bat2sixes": 0,
          "totalRuns": 2,
          "totalBalls": 4,
          "bat1balls": 2,
          "bat2balls": 2,
          "bat1Ones": 1,
          "bat1Twos": 0,
          "bat1Threes": 0,
          "bat1Fives": 0,
          "bat1Boundaries": 0,
          "bat1Sixers": 0,
          "bat2Ones": 1,
          "bat2Twos": 0,
          "bat2Threes": 0,
          "bat2Fives": 0,
          "bat2Boundaries": 0,
          "bat2Sixers": 0
        },
        "pat_6": {
          "bat1Id": 12669,
          "bat1Name": "Prabhudessai",
          "bat1Runs": 10,
          "bat1fours": 1,
          "bat1sixes": 0,
          "bat2Id": 145,
          "bat2Name": "Karthik",
          "bat2Runs": 11,
          "bat2fours": 1,
          "bat2sixes": 0,
          "totalRuns": 22,
          "totalBalls": 16,
          "bat1balls": 9,
          "bat2balls": 7,
          "bat1Ones": 2,
          "bat1Twos": 2,
          "bat1Threes": 0,
          "bat1Fives": 0,
          "bat1Boundaries": 1,
          "bat1Sixers": 0,
          "bat2Ones": 5,
          "bat2Twos": 1,
          "bat2Threes": 0,
          "bat2Fives": 0,
          "bat2Boundaries": 1,
          "bat2Sixers": 0
        },
        "pat_7": {
          "bat1Id": 10926,
          "bat1Name": "Hasaranga",
          "bat1Runs": 5,
          "bat1fours": 0,
          "bat1sixes": 0,
          "bat2Id": 145,
          "bat2Name": "Karthik",
          "bat2Runs": 10,
          "bat2fours": 0,
          "bat2sixes": 1,
          "totalRuns": 15,
          "totalBalls": 12,
          "bat1balls": 4,
          "bat2balls": 8,
          "bat1Ones": 1,
          "bat1Twos": 2,
          "bat1Threes": 0,
          "bat1Fives": 0,
          "bat1Boundaries": 0,
          "bat1Sixers": 0,
          "bat2Ones": 4,
          "bat2Twos": 0,
          "bat2Threes": 0,
          "bat2Fives": 0,
          "bat2Boundaries": 0,
          "bat2Sixers": 1
        },
        "pat_8": {
          "bat1Id": 6592,
          "bat1Name": "Willey",
          "bat1Runs": 2,
          "bat1fours": 0,
          "bat1sixes": 0,
          "bat2Id": 145,
          "bat2Name": "Karthik",
          "bat2Runs": 0,
          "bat2fours": 0,
          "bat2sixes": 0,
          "totalRuns": 2,
          "totalBalls": 4,
          "bat1balls": 3,
          "bat2balls": 1,
          "bat1Ones": 2,
          "bat1Twos": 0,
          "bat1Threes": 0,
          "bat1Fives": 0,
          "bat1Boundaries": 0,
          "bat1Sixers": 0,
          "bat2Ones": 0,
          "bat2Twos": 0,
          "bat2Threes": 0,
          "bat2Fives": 0,
          "bat2Boundaries": 0,
          "bat2Sixers": 0
        },
        "pat_9": {
          "bat1Id": 6592,
          "bat1Name": "Willey",
          "bat1Runs": 9,
          "bat1fours": 1,
          "bat1sixes": 0,
          "bat2Id": 10486,
          "bat2Name": "Vijaykumar Vyshak",
          "bat2Runs": 13,
          "bat2fours": 0,
          "bat2sixes": 1,
          "totalRuns": 25,
          "totalBalls": 15,
          "bat1balls": 7,
          "bat2balls": 8,
          "bat1Ones": 3,
          "bat1Twos": 1,
          "bat1Threes": 0,
          "bat1Fives": 0,
          "bat1Boundaries": 1,
          "bat1Sixers": 0,
          "bat2Ones": 5,
          "bat2Twos": 1,
          "bat2Threes": 0,
          "bat2Fives": 0,
          "bat2Boundaries": 0,
          "bat2Sixers": 1
        }
      }
    }
  ],
  "matchHeader": {
    "matchId": 66484,
    "matchDescription": "36th Match",
    "matchFormat": "T20",
    "matchType": "league",
    "complete": true,
    "domestic": false,
    "matchStartTimestamp": 1682517600000,
    "matchCompleteTimestamp": 1682530872193,
    "dayNight": false,
    "year": 2023,
    "state": "Complete",
    "status": "Kolkata Knight Riders won by 21 runs",
    "tossResults": {
      "tossWinnerId": 59,
      "tossWinnerName": "Royal Challengers Bangalore",
      "decision": "Bowling"
    },
    "result": {
      "resultType": "win",
      "winningTeam": "Kolkata Knight Riders",
      "winningteamId": 63,
      "winningMargin": 21,
      "winByRuns": true,
      "winByInnings": false
    },
    "revisedTarget": { "reason": "" },
    "playersOfTheMatch": [
      {
        "id": 12926,
        "name": "Chakaravarthy",
        "fullName": "Varun Chakaravarthy",
        "nickName": "Chakaravarthy",
        "captain": false,
        "keeper": false,
        "substitute": false,
        "teamName": "Karaikudi Kaalai",
        "faceImageId": 226220
      }
    ],
    "playersOfTheSeries": [],
    "matchTeamInfo": [
      {
        "battingTeamId": 63,
        "battingTeamShortName": "KKR",
        "bowlingTeamId": 59,
        "bowlingTeamShortName": "RCB"
      },
      {
        "battingTeamId": 59,
        "battingTeamShortName": "RCB",
        "bowlingTeamId": 63,
        "bowlingTeamShortName": "KKR"
      }
    ],
    "isMatchNotCovered": false,
    "team1": {
      "id": 59,
      "name": "Royal Challengers Bangalore",
      "playerDetails": [],
      "shortName": "RCB"
    },
    "team2": {
      "id": 63,
      "name": "Kolkata Knight Riders",
      "playerDetails": [],
      "shortName": "KKR"
    },
    "seriesDesc": "Indian Premier League 2023",
    "seriesId": 5945,
    "seriesName": "Indian Premier League 2023",
    "alertType": "auto",
    "livestreamEnabled": false
  },
  "isMatchComplete": true,
  "status": "Kolkata Knight Riders won by 21 runs",
  "videos": [],
  "responseLastUpdated": 1713685517
}
